pdfcli.py
pdfcli-0.0.6.dist-info/LICENSE
pdfcli-0.0.6.dist-info/METADATA
pdfcli-0.0.6.dist-info/WHEEL
pdfcli-0.0.6.dist-info/entry_points.txt
pdfcli-0.0.6.dist-info/top_level.txt
pdfcli-0.0.6.dist-info/RECORD
