Metadata-Version: 2.1
Name: pdfcli
Version: 0.0.6
Summary: Simplify manipulating PDFs
Home-page: https://github.com/oliviersm199/pdfcli
Author: Olivier Simard-Morissette
Author-email: olivier.morissette@gmail.com
License: MIT
Platform: UNKNOWN
Requires-Python: >=3.5
Requires-Dist: Click (<8.0,>=7.0)
Requires-Dist: PyPDF2 (<2.0,>=1.26.0)
